lazr.config-3.1-py3.11-nspkg.pth
lazr/config/__init__.py
lazr/config/_config.py
lazr/config/_version.py
lazr/config/interfaces.py
lazr/config/docs/CONTRIBUTING.rst
lazr/config/docs/NEWS.rst
lazr/config/docs/__init__.py
lazr/config/docs/conf.py
lazr/config/docs/index.rst
lazr/config/tests/__init__.py
lazr/config/tests/test_config.py
lazr/config/tests/test_docs.py
lazr/config/tests/testdata/__init__.py
lazr/config/tests/testdata/bad-invalid-name-chars.conf
lazr/config/tests/testdata/bad-invalid-name.conf
lazr/config/tests/testdata/bad-nonascii.conf
lazr/config/tests/testdata/bad-redefined-key.conf
lazr/config/tests/testdata/bad-redefined-section.conf
lazr/config/tests/testdata/bad-sectionless.conf
lazr/config/tests/testdata/base.conf
lazr/config/tests/testdata/local.conf
lazr/config/tests/testdata/master-local.conf
lazr/config/tests/testdata/master.conf
lazr/config/tests/testdata/shared.conf
lazr.config-3.1.dist-info/COPYING.txt
lazr.config-3.1.dist-info/METADATA
lazr.config-3.1.dist-info/WHEEL
lazr.config-3.1.dist-info/namespace_packages.txt
lazr.config-3.1.dist-info/top_level.txt
lazr.config-3.1.dist-info/RECORD
