Metadata-Version: 2.1
Name: lazr.config
Version: 3.1
Summary: Create configuration schemas, and process and validate configurations.
Home-page: https://launchpad.net/lazr.config
Download-URL: https://launchpad.net/lazr.config/+download
Maintainer: LAZR Developers
Maintainer-email: lazr-developers@lists.launchpad.net
License: LGPL v3
Project-URL: Source, https://code.launchpad.net/lazr.config
Project-URL: Issue Tracker, https://bugs.launchpad.net/lazr.config
Project-URL: Documentation, https://lazrconfig.readthedocs.io/en/latest/
Classifier: Development Status :: 5 - Production/Stable
Classifier: Intended Audience :: Developers
Classifier: License :: OSI Approved :: GNU Library or Lesser General Public License (LGPL)
Classifier: Operating System :: OS Independent
Classifier: Programming Language :: Python
Classifier: Programming Language :: Python :: 3
Classifier: Programming Language :: Python :: 3.8
Classifier: Programming Language :: Python :: 3.9
Classifier: Programming Language :: Python :: 3.10
Classifier: Programming Language :: Python :: 3.11
Classifier: Programming Language :: Python :: 3.12
Classifier: Programming Language :: Python :: 3.13
Requires-Python: >=3.8
License-File: COPYING.txt
Requires-Dist: setuptools
Requires-Dist: zope.interface
Requires-Dist: lazr.delegates
Provides-Extra: docs
Requires-Dist: Sphinx; extra == "docs"
